colbert_live/__init__.py
colbert_live/colbert_live.py
colbert_live/models.py
colbert_live/py.typed
colbert_live/db/__init__.py
colbert_live/db/astra.py
colbert_live/db/db.py
colbert_live/db/sqlite.py
colbert_live-0.9.0.dist-info/LICENSE.txt
colbert_live-0.9.0.dist-info/METADATA
colbert_live-0.9.0.dist-info/WHEEL
colbert_live-0.9.0.dist-info/top_level.txt
colbert_live-0.9.0.dist-info/RECORD
