Metadata-Version: 2.1
Name: colbert-live
Version: 0.9.0
Summary: ColBERT Live! implements efficient ColBERT and ColPaLi search on top of vector indexes that support live updates (without rebuilding the entire index)
Author-email: Jonathan Ellis <jbellis@gmail.com>
Project-URL: Homepage, https://github.com/jbellis/colbert-live
Project-URL: Issues, https://github.com/jbellis/colbert-live/issues
Classifier: Programming Language :: Python :: 3
Classifier: License :: OSI Approved :: Apache Software License
Classifier: Operating System :: OS Independent
Classifier: Development Status :: 4 - Beta
Classifier: Intended Audience :: Developers
Classifier: Topic :: Scientific/Engineering :: Artificial Intelligence
Classifier: Topic :: Text Processing :: Indexing
Requires-Python: >=3.9
License-File: LICENSE.txt
Requires-Dist: colbert-ai ==0.2.20
Requires-Dist: torch >=1.13
Requires-Dist: colpali-engine <0.4.0,>=0.3.1
Requires-Dist: pillow
Requires-Dist: scikit-learn
